vpn_slice/__init__.py
vpn_slice/__main__.py
vpn_slice/dnspython.py
vpn_slice/freebsd.py
vpn_slice/linux.py
vpn_slice/mac.py
vpn_slice/posix.py
vpn_slice/provider.py
vpn_slice/util.py
vpn_slice/version.py
vpn_slice-0.16.1.dist-info/LICENSE.txt
vpn_slice-0.16.1.dist-info/METADATA
vpn_slice-0.16.1.dist-info/WHEEL
vpn_slice-0.16.1.dist-info/entry_points.txt
vpn_slice-0.16.1.dist-info/top_level.txt
vpn_slice-0.16.1.dist-info/RECORD
