Metadata-Version: 2.1
Name: vpn-slice
Version: 0.16.1
Summary: vpnc-script replacement for easy split-tunnel VPN setup
Home-page: https://github.com/dlenski/vpn-slice
Author: Daniel Lenski
Author-email: dlenski@gmail.com
License: GPL v3 or later
Platform: UNKNOWN
Classifier: License :: OSI Approved :: GNU General Public License v3 or later (GPLv3+)
Classifier: Operating System :: MacOS :: MacOS X
Classifier: Operating System :: POSIX :: BSD
Classifier: Topic :: System :: Systems Administration
Classifier: Operating System :: POSIX :: Linux
Classifier: Topic :: System :: Networking
Classifier: Environment :: Console
Classifier: Development Status :: 4 - Beta
Provides-Extra: setproctitle
Provides-Extra: dnspython
License-File: LICENSE.txt
